guard_me/__init__.py
guard_me/__main__.py
guard_me/main.py
guardme-1.0.1.data/scripts/guardme
guardme-1.0.1.dist-info/DESCRIPTION.rst
guardme-1.0.1.dist-info/METADATA
guardme-1.0.1.dist-info/RECORD
guardme-1.0.1.dist-info/WHEEL
guardme-1.0.1.dist-info/metadata.json
guardme-1.0.1.dist-info/top_level.txt
