Metadata-Version: 2.0
Name: guardme
Version: 1.0.1
Summary: To save username and password
Home-page: https://github.com/dhirajshah04/guardme
Author: Dhiraj Shah
Author-email: dhiraj.shah04@gmail.com
License: UNKNOWN
Platform: UNKNOWN
Classifier: Environment :: Console
Classifier: Programming Language :: Python :: 3
Requires-Dist: pyperclip
